env/__init__.py
env/core.py
env/main.py
env/py.typed
parsenv-0.3.0.dist-info/WHEEL
parsenv-0.3.0.dist-info/METADATA
parsenv-0.3.0.dist-info/RECORD
