Metadata-Version: 2.1
Name: parsenv
Version: 0.3.0
Summary: Typed dotenv parser
License: MIT
Author-email: levch <levchenko.d.a1998@gmail.com>
Requires-Python: >=3.10
Requires-Dist: typenv>=0.2.0
